{"cameraMode":{"drawMode":0,"name":"Shaded","section":"Shading Mode"},"sceneLighting":false,"audioPlay":false,"sceneViewState":{"m_AlwaysRefresh":false,"showFog":true,"showSkybox":false,"showFlares":true,"showImageEffects":true,"showParticleSystems":true,"showVisualEffectGraphs":true,"m_FxEnabled":true},"in2DMode":false,"pivot":{"x":-0.9598739743232727,"y":-0.6853345632553101,"z":0.09771512448787689},"rotation":{"x":0.196358323097229,"y":-0.6934089064598084,"z":0.20564325153827668,"w":0.6620808839797974},"size":1.0426743030548096,"orthographic":false}